ocellus/__init__.py
ocellus/ocellus_dataflow_service_pb2.py
ocellus/ocellus_dataflow_service_pb2_grpc.py
ocellus/ocellus_module_service_pb2.py
ocellus/ocellus_module_service_pb2_grpc.py
ocellus/ocellus_types_pb2.py
ocellus/ocellus_types_pb2_grpc.py
ocellus/api/v1/__init__.py
ocellus/api/v1/ocellus_api_command_service_pb2.py
ocellus/api/v1/ocellus_api_command_service_pb2_grpc.py
ocellus/api/v1/ocellus_api_module_config_pb2.py
ocellus/api/v1/ocellus_api_module_config_pb2_grpc.py
ocellus/api/v1/ocellus_api_module_data_service_pb2.py
ocellus/api/v1/ocellus_api_module_data_service_pb2_grpc.py
ocellus/api/v1/ocellus_api_module_info_service_pb2.py
ocellus/api/v1/ocellus_api_module_info_service_pb2_grpc.py
ocellus/google/api/annotations_pb2.py
ocellus/google/api/annotations_pb2_grpc.py
ocellus/google/api/auth_pb2.py
ocellus/google/api/auth_pb2_grpc.py
ocellus/google/api/backend_pb2.py
ocellus/google/api/backend_pb2_grpc.py
ocellus/google/api/billing_pb2.py
ocellus/google/api/billing_pb2_grpc.py
ocellus/google/api/client_pb2.py
ocellus/google/api/client_pb2_grpc.py
ocellus/google/api/config_change_pb2.py
ocellus/google/api/config_change_pb2_grpc.py
ocellus/google/api/consumer_pb2.py
ocellus/google/api/consumer_pb2_grpc.py
ocellus/google/api/context_pb2.py
ocellus/google/api/context_pb2_grpc.py
ocellus/google/api/control_pb2.py
ocellus/google/api/control_pb2_grpc.py
ocellus/google/api/distribution_pb2.py
ocellus/google/api/distribution_pb2_grpc.py
ocellus/google/api/documentation_pb2.py
ocellus/google/api/documentation_pb2_grpc.py
ocellus/google/api/endpoint_pb2.py
ocellus/google/api/endpoint_pb2_grpc.py
ocellus/google/api/field_behavior_pb2.py
ocellus/google/api/field_behavior_pb2_grpc.py
ocellus/google/api/http_pb2.py
ocellus/google/api/http_pb2_grpc.py
ocellus/google/api/httpbody_pb2.py
ocellus/google/api/httpbody_pb2_grpc.py
ocellus/google/api/label_pb2.py
ocellus/google/api/label_pb2_grpc.py
ocellus/google/api/launch_stage_pb2.py
ocellus-0.1.91.dist-info/LICENSE
ocellus-0.1.91.dist-info/METADATA
ocellus-0.1.91.dist-info/WHEEL
ocellus-0.1.91.dist-info/top_level.txt
ocellus-0.1.91.dist-info/RECORD
