Metadata-Version: 2.1
Name: ocellus
Version: 0.1.91
Summary: Ocellus API Python Client
Home-page: https://docs.ocellus.io/
Author: Byte Motion AB
Author-email: python@bytemotion.se
License: MIT
Platform: UNKNOWN
Classifier: Intended Audience :: Developers
Classifier: License :: OSI Approved :: MIT License
Classifier: Programming Language :: Python
Classifier: Programming Language :: Python :: 3
Classifier: Programming Language :: Python :: 3.6
Classifier: Programming Language :: Python :: 3.7
Classifier: Programming Language :: Python :: 3.8
Classifier: Programming Language :: Python :: 3.9
Classifier: Operating System :: OS Independent
License-File: LICENSE
Requires-Dist: grpcio (==1.43.0)
Requires-Dist: protobuf (==3.19.3)
